ua_clarity_tools/__init__.py
ua_clarity_tools/api_types.py
ua_clarity_tools/batch_artifact_update_template.xml
ua_clarity_tools/routing_template.xml
ua_clarity_tools/ua_clarity_tools.py
mu_test-1.1.9.dist-info/LICENSE
mu_test-1.1.9.dist-info/METADATA
mu_test-1.1.9.dist-info/WHEEL
mu_test-1.1.9.dist-info/top_level.txt
mu_test-1.1.9.dist-info/RECORD
