Metadata-Version: 2.1
Name: mu-test
Version: 1.1.9
Summary: API that interacts with Illumina's Clarity LIMS software at a higher level than requests.
Home-page: https://github.com/UACoreFacilitiesIT/UA-Clarity-Tools
Author: Michael
Author-email: muebele@arizona.edu
License: MIT
License-File: LICENSE
Requires-Dist: requests
Requires-Dist: bs4
Requires-Dist: lxml
Requires-Dist: jinja2
Requires-Dist: ua-clarity-api
Requires-Dist: nose
Requires-Dist: dataclasses
